compliance/__init__.py
compliance/agent.py
compliance/check.py
compliance/config.py
compliance/controls.py
compliance/evidence.py
compliance/fetch.py
compliance/fix.py
compliance/locker.py
compliance/notify.py
compliance/report.py
compliance/runners.py
compliance/scripts/__init__.py
compliance/scripts/compliance_cli.py
compliance/templates/readme_toc.md.tmpl
compliance/utils/__init__.py
compliance/utils/credentials.py
compliance/utils/data_parse.py
compliance/utils/exceptions.py
compliance/utils/fetch_local_commands
compliance/utils/http.py
compliance/utils/path.py
compliance/utils/test.py
compliance/utils/services/__init__.py
compliance/utils/services/github.py
compliance/utils/services/pagerduty.py
auditree_framework-2.0.0.dist-info/LICENSE
auditree_framework-2.0.0.dist-info/METADATA
auditree_framework-2.0.0.dist-info/WHEEL
auditree_framework-2.0.0.dist-info/entry_points.txt
auditree_framework-2.0.0.dist-info/top_level.txt
auditree_framework-2.0.0.dist-info/RECORD
