Metadata-Version: 2.1
Name: auditree-framework
Version: 2.0.0
Summary: Tool to run compliance control checks as unit tests
Home-page: https://auditree.github.io/
Author: Auditree Security and Compliance
Author-email: al.finkelstein@ibm.com
License: Apache License 2.0
Classifier: Programming Language :: Python :: 3.6
Classifier: Programming Language :: Python :: 3.7
Classifier: Programming Language :: Python :: 3.8
Classifier: Programming Language :: Python :: 3.9
Classifier: License :: OSI Approved :: Apache Software License
Classifier: Operating System :: MacOS :: MacOS X
Classifier: Operating System :: POSIX :: Linux
License-File: LICENSE
Requires-Dist: inflection (>=0.3.1)
Requires-Dist: GitPython (>=2.1.3)
Requires-Dist: jinja2 (>=2.10)
Requires-Dist: ibm-cloud-security-advisor (>=2.0.0)
Requires-Dist: ilcli (>=0.3.1)
Requires-Dist: cryptography (>=35.0.0)
Provides-Extra: dev
Requires-Dist: pytest (>=5.4.3) ; extra == 'dev'
Requires-Dist: pytest-cov (>=2.10.0) ; extra == 'dev'
Requires-Dist: pre-commit (>=2.4.0) ; extra == 'dev'
Requires-Dist: Sphinx (>=1.7.2) ; extra == 'dev'
Requires-Dist: setuptools ; extra == 'dev'
Requires-Dist: wheel ; extra == 'dev'
Requires-Dist: twine ; extra == 'dev'
